apto/__init__.py
apto/__version__.py
apto/settings.py
apto/sklearn.py
apto/utils/__init__.py
apto/utils/misc.py
apto/utils/report.py
apto/utils/thresholds.py
apto/utils/visualization.py
apto-0.0.2.dist-info/LICENSE
apto-0.0.2.dist-info/METADATA
apto-0.0.2.dist-info/WHEEL
apto-0.0.2.dist-info/top_level.txt
apto-0.0.2.dist-info/RECORD
