Metadata-Version: 2.1
Name: apto
Version: 0.0.2
Summary: Apto.
Home-page: UNKNOWN
Author: 
Author-email: 
License: Apache License 2.0
Keywords: Machine Learning
Platform: UNKNOWN
Classifier: Environment :: Console
Classifier: Natural Language :: English
Classifier: Development Status :: 4 - Beta
Classifier: Operating System :: OS Independent
Classifier: License :: OSI Approved :: Apache Software License
Classifier: Intended Audience :: Developers
Classifier: Intended Audience :: Science/Research
Classifier: Topic :: Scientific/Engineering :: Artificial Intelligence
Classifier: Topic :: Scientific/Engineering :: Information Analysis
Classifier: Programming Language :: Python
Classifier: Programming Language :: Python :: 3.6
Classifier: Programming Language :: Python :: 3.7
Classifier: Programming Language :: Python :: 3.8
Classifier: Programming Language :: Python :: 3.9
Classifier: Programming Language :: Python :: 3.10
Classifier: Programming Language :: Python :: Implementation :: CPython
Requires-Python: >=3.6.0
License-File: LICENSE
Requires-Dist: numpy
Requires-Dist: pandas (>=1.0.0)
Requires-Dist: scikit-learn (>=1.0)
